pyproject.toml
reading_helper/__init__.py
reading_helper/make_paper_page.py
reading_helper/scripts_api.py
reading_helper/search_tags.py
template.md
reading_helper-0.1.7.dist-info/entry_points.txt
reading_helper-0.1.7.dist-info/LICENSE
reading_helper-0.1.7.dist-info/WHEEL
reading_helper-0.1.7.dist-info/METADATA
reading_helper-0.1.7.dist-info/RECORD
